pulpcore/__init__.py
pulpcore/client/__init__.py
pulpcore/client/pulp_container/__init__.py
pulpcore/client/pulp_container/api_client.py
pulpcore/client/pulp_container/api_response.py
pulpcore/client/pulp_container/configuration.py
pulpcore/client/pulp_container/exceptions.py
pulpcore/client/pulp_container/py.typed
pulpcore/client/pulp_container/rest.py
pulpcore/client/pulp_container/api/__init__.py
pulpcore/client/pulp_container/api/content_blobs_api.py
pulpcore/client/pulp_container/api/content_manifests_api.py
pulpcore/client/pulp_container/api/content_signatures_api.py
pulpcore/client/pulp_container/api/content_tags_api.py
pulpcore/client/pulp_container/api/distributions_container_api.py
pulpcore/client/pulp_container/api/distributions_pull_through_api.py
pulpcore/client/pulp_container/api/pulp_container_namespaces_api.py
pulpcore/client/pulp_container/api/remotes_container_api.py
pulpcore/client/pulp_container/api/remotes_pull_through_api.py
pulpcore/client/pulp_container/api/repositories_container_api.py
pulpcore/client/pulp_container/api/repositories_container_push_api.py
pulpcore/client/pulp_container/api/repositories_container_push_versions_api.py
pulpcore/client/pulp_container/api/repositories_container_versions_api.py
pulpcore/client/pulp_container/api/token_api.py
pulpcore/client/pulp_container/models/__init__.py
pulpcore/client/pulp_container/models/async_operation_response.py
pulpcore/client/pulp_container/models/container_blob_response.py
pulpcore/client/pulp_container/models/container_container_distribution.py
pulpcore/client/pulp_container/models/container_container_distribution_response.py
pulpcore/client/pulp_container/models/container_container_namespace.py
pulpcore/client/pulp_container/models/container_container_namespace_response.py
pulpcore/client/pulp_container/models/container_container_pull_through_distribution.py
pulpcore/client/pulp_container/models/container_container_pull_through_distribution_response.py
pulp_container_client-2.27.0.dist-info/METADATA
pulp_container_client-2.27.0.dist-info/WHEEL
pulp_container_client-2.27.0.dist-info/top_level.txt
pulp_container_client-2.27.0.dist-info/RECORD
